[{
  "_id": {
    "$oid": "5f9451c2441f9facb64fb014"
  },
  "UserName": "Jhon Smith",
  "Password": "1234",
  "Email": "JS@Gmailo.com",
  "Birthday": "01/01/1990",
  "FavotiteMovies": []
},{
  "_id": {
    "$oid": "5f9451c2441f9facb64fb015"
  },
  "UserName": "Mike Smith",
  "Password": "4321",
  "Email": "MS@Gmailo.com",
  "Birthday": "01/01/1991",
  "FavotiteMovies": []
},{
  "_id": {
    "$oid": "5f9451c2441f9facb64fb016"
  },
  "UserName": "Mary Piterson",
  "Password": "1524",
  "Email": "MP@Gmailo.com",
  "Birthday": "03/03/1990",
  "FavotiteMovies": []
},{
  "_id": {
    "$oid": "5f9451c2441f9facb64fb017"
  },
  "UserName": "Jhon Piterson",
  "Password": "1542",
  "Email": "JP@Gmailo.com",
  "Birthday": "01/01/1985",
  "FavotiteMovies": []
},{
  "_id": {
    "$oid": "5f9451c2441f9facb64fb018"
  },
  "UserName": "Sam Smith",
  "Password": "1234",
  "Email": "SS@Gmailo.com",
  "Birthday": "11/01/1999",
  "FavotiteMovies": []
}]